rage_toolkit/__init__.py
rage_toolkit/cite_evaluation.py
rage_toolkit/cite_evaluation_utils.py
rage_toolkit/types.py
rage_toolkit-0.0.2.dist-info/LICENSE
rage_toolkit-0.0.2.dist-info/METADATA
rage_toolkit-0.0.2.dist-info/WHEEL
rage_toolkit-0.0.2.dist-info/top_level.txt
rage_toolkit-0.0.2.dist-info/RECORD
