Metadata-Version: 2.1
Name: rage-toolkit
Version: 0.0.2
Summary: A framework for retrieval augmented generation evaluation (RAGE)
Home-page: https://github.com/othr-nlp/rage_toolkit
Author: Vinzent Penzkofer, Timo Baumann
Author-email: vinzent.penzkofer@outlook.de, timo.baumann@oth-regensburg.de
License: MIT
Project-URL: Documentation, https://github.com/othr-nlp/rage_toolkit
Keywords: retrieval,augmented generation,evaluation,RAG,NLP
Classifier: Programming Language :: Python :: 3
Classifier: License :: OSI Approved :: MIT License
Classifier: Operating System :: OS Independent
Requires-Python: >=3.6
License-File: LICENSE
Requires-Dist: pandas
